gage_summary/__init__.py
gage_summary/_test_support.py
gage_summary-0.1.1.dist-info/LICENSE.txt
gage_summary-0.1.1.dist-info/METADATA
gage_summary-0.1.1.dist-info/WHEEL
gage_summary-0.1.1.dist-info/top_level.txt
gage_summary-0.1.1.dist-info/RECORD
